wavesim/__init__.py
wavesim/domain.py
wavesim/engine/__init__.py
wavesim/engine/array.py
wavesim/engine/blockarray.py
wavesim/engine/constantarray.py
wavesim/engine/cupyarray.py
wavesim/engine/dispatcher.py
wavesim/engine/functions.py
wavesim/engine/index_utils.py
wavesim/engine/numpyarray.py
wavesim/engine/sparsearray.py
wavesim/helmholtzdomain.py
wavesim/iteration.py
wavesim/maxwelldomain.py
wavesim/simulate.py
wavesim/utilities/__init__.py
wavesim/utilities/create_medium.py
wavesim/utilities/create_source.py
wavesim/wrapcorrecteddomain.py
wavesim-0.2.0a1.dist-info/licenses/LICENSE
wavesim-0.2.0a1.dist-info/METADATA
wavesim-0.2.0a1.dist-info/WHEEL
wavesim-0.2.0a1.dist-info/RECORD
