Metadata-Version: 2.4
Name: wavesim
Version: 0.2.0a1
Summary: A library for simulating wave propagation using the modified Born series
License-File: LICENSE
Author: Ivo Vellekoop
Author-email: i.m.vellekoop@utwente.nl
Requires-Python: >=3.11,<4.0
Classifier: Programming Language :: Python :: 3
Classifier: Operating System :: OS Independent
Requires-Dist: cupy-cuda12x (>=13.4.1,<14.0.0)
Requires-Dist: numba (>=0.60.0)
Requires-Dist: scipy (>=1.15.0,<2.0.0)
